pyschemaelectrical/__init__.py
pyschemaelectrical/builder.py
pyschemaelectrical/layout/__init__.py
pyschemaelectrical/layout/layout.py
pyschemaelectrical/layout/wire_labels.py
pyschemaelectrical/model/__init__.py
pyschemaelectrical/model/constants.py
pyschemaelectrical/model/core.py
pyschemaelectrical/model/parts.py
pyschemaelectrical/model/primitives.py
pyschemaelectrical/std_circuits/__init__.py
pyschemaelectrical/std_circuits/control.py
pyschemaelectrical/std_circuits/motor.py
pyschemaelectrical/std_circuits/power.py
pyschemaelectrical/std_circuits/safety.py
pyschemaelectrical/symbols/__init__.py
pyschemaelectrical/symbols/actuators.py
pyschemaelectrical/symbols/assemblies.py
pyschemaelectrical/symbols/blocks.py
pyschemaelectrical/symbols/breakers.py
pyschemaelectrical/symbols/coils.py
pyschemaelectrical/symbols/contacts.py
pyschemaelectrical/symbols/protection.py
pyschemaelectrical/symbols/references.py
pyschemaelectrical/symbols/terminals.py
pyschemaelectrical/symbols/transducers.py
pyschemaelectrical/system/__init__.py
pyschemaelectrical/system/connection_registry.py
pyschemaelectrical/system/system.py
pyschemaelectrical/system/system_analysis.py
pyschemaelectrical/utils/__init__.py
pyschemaelectrical/utils/autonumbering.py
pyschemaelectrical/utils/export_utils.py
pyschemaelectrical/utils/renderer.py
pyschemaelectrical/utils/terminal_bridges.py
pyschemaelectrical/utils/transform.py
pyschemaelectrical/utils/utils.py
pyschemaelectrical-0.1.6.dist-info/licenses/LICENSE
pyschemaelectrical-0.1.6.dist-info/METADATA
pyschemaelectrical-0.1.6.dist-info/WHEEL
pyschemaelectrical-0.1.6.dist-info/top_level.txt
pyschemaelectrical-0.1.6.dist-info/RECORD
