Metadata-Version: 2.4
Name: pyschemaelectrical
Version: 0.1.6
Summary: A Python library for creating electrical schematic diagrams programmatically
Author: Ole Johan Bondahl
License: MIT License
Project-URL: Homepage, https://github.com/OleJBondahl/PySchemaElectrical
Project-URL: Repository, https://github.com/OleJBondahl/PySchemaElectrical
Project-URL: Issues, https://github.com/OleJBondahl/PySchemaElectrical/issues
Keywords: electrical,schematic,diagram,svg,iec
Classifier: Development Status :: 3 - Alpha
Classifier: Intended Audience :: Developers
Classifier: Topic :: Scientific/Engineering :: Electronic Design Automation (EDA)
Classifier: License :: OSI Approved :: MIT License
Classifier: Programming Language :: Python :: 3
Classifier: Programming Language :: Python :: 3.8
Classifier: Programming Language :: Python :: 3.9
Classifier: Programming Language :: Python :: 3.10
Classifier: Programming Language :: Python :: 3.11
Classifier: Programming Language :: Python :: 3.12
Requires-Python: >=3.8
License-File: LICENSE
Dynamic: license-file
